multithread/__init__.py
multithread-1.0.1.dist-info/LICENSE
multithread-1.0.1.dist-info/METADATA
multithread-1.0.1.dist-info/WHEEL
multithread-1.0.1.dist-info/top_level.txt
multithread-1.0.1.dist-info/RECORD
