Metadata-Version: 2.1
Name: multithread
Version: 1.0.1
Summary: An optionally asynchronous multithreaded downloader for python
Home-page: https://github.com/DashLt/multithread
Author: DashLt
License: UNKNOWN
Platform: UNKNOWN
Classifier: Programming Language :: Python :: 3
Classifier: License :: OSI Approved :: MIT License
Classifier: Operating System :: OS Independent
Classifier: Development Status :: 4 - Beta
Classifier: Framework :: AsyncIO
Classifier: Topic :: Internet :: WWW/HTTP
Requires-Python: >3.5
Provides-Extra: progress
